country_iso2ify/__init__.py
country_iso2ify/default_aliases.py
country_iso2ify/resolver.py
country_iso2ify-0.1.3.dist-info/licenses/LICENSE
country_iso2ify-0.1.3.dist-info/METADATA
country_iso2ify-0.1.3.dist-info/WHEEL
country_iso2ify-0.1.3.dist-info/top_level.txt
country_iso2ify-0.1.3.dist-info/RECORD
