Metadata-Version: 2.4
Name: country-iso2ify
Version: 0.1.3
Summary: Pure-Python country name to ISO-3166 alpha-2 resolver with custom aliases.
Author-email: M Azeem Akhter <azeem3ch@gmail.com>
License: MIT
Requires-Python: >=3.9
License-File: LICENSE
Requires-Dist: pycountry>=22.3.5
Requires-Dist: boto3>=1.34.0
Requires-Dist: requests>=2.31.0
Dynamic: license-file
